__pyinstaller/__init__.py
pygrafical/__init__.py
pygrafical/lib.so
pygrafical/main.py
pygrafical/hooks/hook-pygrafical.py
pygrafical-0.0.19.dist-info/LICENSE
pygrafical-0.0.19.dist-info/METADATA
pygrafical-0.0.19.dist-info/WHEEL
pygrafical-0.0.19.dist-info/top_level.txt
pygrafical-0.0.19.dist-info/RECORD
