Metadata-Version: 2.1
Name: pygrafical
Version: 0.0.19
Summary: графическая библиотека основаная на Windows API
Home-page: https://github.com/Ananimys784/Kingurio
Author: tetredial_9274
Author-email: system32@mail.ru
Classifier: Programming Language :: Python :: 3
Classifier: License :: OSI Approved :: MIT License
Classifier: Operating System :: OS Independent
Requires-Python: >=3.6
License-File: LICENSE
